qic/Frenet_to_cylindrical.py
qic/__init__.py
qic/calculate_r1.py
qic/calculate_r2.py
qic/calculate_r3.py
qic/fourier_interpolation.py
qic/grad_B_tensor.py
qic/init_axis.py
qic/mercier.py
qic/newton.py
qic/optimize_nae.py
qic/plot.py
qic/qic.py
qic/r_singularity.py
qic/spectral_diff_matrix.py
qic/to_vmec.py
qic/util.py
qic/tests/__init__.py
qic/tests/test_fourier_interpolation.py
qic/tests/test_grad_B_tensor.py
qic/tests/test_newton.py
qic/tests/test_omnigenity.py
qic/tests/test_omnigenity_r2.py
qic/tests/test_plot.py
qic/tests/test_qsc.py
qic/tests/test_spectral_diff_matrix.py
qic/tests/test_to_vmec.py
qic/tests/test_util.py
qicna-0.3.6.dist-info/licenses/LICENSE
qicna-0.3.6.dist-info/METADATA
qicna-0.3.6.dist-info/WHEEL
qicna-0.3.6.dist-info/top_level.txt
qicna-0.3.6.dist-info/RECORD
