Metadata-Version: 2.4
Name: qicna
Version: 0.3.6
Summary: Quasi-isodynamic Stellarator Construction
Home-page: https://github.com/rogeriojorge/pyQIC
Author: Rogerio Jorge and Matt Landreman
Author-email: rogerio.jorge@tecnico.ulisboa.pt
License: MIT
Classifier: Programming Language :: Python :: 3
Classifier: License :: OSI Approved :: MIT License
Classifier: Operating System :: OS Independent
Requires-Python: >=3.6
License-File: LICENSE
Dynamic: author
Dynamic: author-email
Dynamic: classifier
Dynamic: description
Dynamic: description-content-type
Dynamic: home-page
Dynamic: license
Dynamic: license-file
Dynamic: requires-python
Dynamic: summary
